appc/__init__.py
appc/core.py
appc/main.py
appc/py.typed
appc-0.0.1.dev20251209110701.dist-info/WHEEL
appc-0.0.1.dev20251209110701.dist-info/METADATA
appc-0.0.1.dev20251209110701.dist-info/RECORD
