Metadata-Version: 2.3
Name: appc
Version: 0.0.1.dev20251209110701
Summary: Add your description here
Author: Chen Peng
License: MIT
Requires-Dist: requests>=2.32.5
Requires-Python: >=3.12
Project-URL: homepage, https://github.com/chen56/appc
